autonomous_general_agent_swarm/__init__.py
autonomous_general_agent_swarm/actions/__init__.py
autonomous_general_agent_swarm/actions/action_space.json
autonomous_general_agent_swarm/actions/code/__init__.py
autonomous_general_agent_swarm/actions/memory/__init__.py
autonomous_general_agent_swarm/actions/memory/retrieval/__init__.py
autonomous_general_agent_swarm/actions/memory/retrieval/default_file_retrieval.py
autonomous_general_agent_swarm/actions/memory/upload/__init__.py
autonomous_general_agent_swarm/actions/memory/upload/default_file_upload.py
autonomous_general_agent_swarm/core/__init__.py
autonomous_general_agent_swarm/core/agents/__init__.py
autonomous_general_agent_swarm/core/agents/executor.py
autonomous_general_agent_swarm/core/swarm/__init__.py
autonomous_general_agent_swarm/core/swarm/configuration_utils.py
autonomous_general_agent_swarm/core/swarm/file_storage_config.py
autonomous_general_agent_swarm/core/swarm/swarm_blueprint.py
autonomous_general_agent_swarm/ignore/old_swarm/actions/__init__.py
autonomous_general_agent_swarm/ignore/old_swarm/actions/_node_info.json
autonomous_general_agent_swarm/ignore/old_swarm/actions/action_router/__init__.py
autonomous_general_agent_swarm/ignore/old_swarm/actions/action_router/_node_info.json
autonomous_general_agent_swarm/ignore/old_swarm/actions/action_router/script.py
autonomous_general_agent_swarm/ignore/old_swarm/actions/action_router/tool.json
autonomous_general_agent_swarm/ignore/old_swarm/actions/code/__init__.py
autonomous_general_agent_swarm/ignore/old_swarm/actions/code/_node_info.json
autonomous_general_agent_swarm/ignore/old_swarm/actions/code/python_coder/__init__.py
autonomous_general_agent_swarm/ignore/old_swarm/actions/code/python_coder/_node_info.json
autonomous_general_agent_swarm/ignore/old_swarm/actions/code/python_coder/description.md
autonomous_general_agent_swarm/ignore/old_swarm/actions/code/python_coder/script.py
autonomous_general_agent_swarm-0.1.0.dist-info/LICENSE
autonomous_general_agent_swarm-0.1.0.dist-info/METADATA
autonomous_general_agent_swarm-0.1.0.dist-info/WHEEL
autonomous_general_agent_swarm-0.1.0.dist-info/RECORD
