Metadata-Version: 2.1
Name: autonomous_general_agent_swarm
Version: 0.1.0
Summary: 
Author: BrianP8701
Author-email: brianp8701@gmail.com
Requires-Python: >=3.10,<4.0
Classifier: Programming Language :: Python :: 3
Classifier: Programming Language :: Python :: 3.10
Classifier: Programming Language :: Python :: 3.11
Requires-Dist: importlib (>=1.0.4,<2.0.0)
Requires-Dist: pydantic (>=2.5.3,<3.0.0)
